<annotation>
	<folder>images</folder>
	<filename>4cc9d74e-679d-11e5-90f4-40f2e96c8ad8.jpg</filename>
	<path>C:\Users\Akashdeep\Desktop\paper\images\garbage-dataset\images\4cc9d74e-679d-11e5-90f4-40f2e96c8ad8.jpg</path>
	<source>
		<database>Unknown</database>
	</source>
	<size>
		<width>683</width>
		<height>1024</height>
		<depth>3</depth>
	</size>
	<segmented>0</segmented>
	<object>
		<name>garbage</name>
		<pose>Unspecified</pose>
		<truncated>1</truncated>
		<difficult>0</difficult>
		<bndbox>
			<xmin>256</xmin>
			<ymin>137</ymin>
			<xmax>676</xmax>
			<ymax>1024</ymax>
		</bndbox>
	</object>
	<object>
		<name>garbage</name>
		<pose>Unspecified</pose>
		<truncated>1</truncated>
		<difficult>0</difficult>
		<bndbox>
			<xmin>566</xmin>
			<ymin>39</ymin>
			<xmax>683</xmax>
			<ymax>113</ymax>
		</bndbox>
	</object>
	<object>
		<name>garbage</name>
		<pose>Unspecified</pose>
		<truncated>0</truncated>
		<difficult>0</difficult>
		<bndbox>
			<xmin>19</xmin>
			<ymin>515</ymin>
			<xmax>390</xmax>
			<ymax>691</ymax>
		</bndbox>
	</object>
	<object>
		<name>garbage</name>
		<pose>Unspecified</pose>
		<truncated>0</truncated>
		<difficult>0</difficult>
		<bndbox>
			<xmin>3</xmin>
			<ymin>696</ymin>
			<xmax>151</xmax>
			<ymax>972</ymax>
		</bndbox>
	</object>
</annotation>
